[
  {
    "ContainingType": "AuthorWebsiteAPI.Controllers.AuthController",
    "Method": "ForgotPassword",
    "RelativePath": "api/Auth/forgot-password",
    "HttpMethod": "POST",
    "IsController": true,
    "Order": 0,
    "Parameters": [
      {
        "Name": "dto",
        "Type": "AuthorWebsiteAPI.DTOs.ForgotDto",
        "IsRequired": true
      }
    ],
    "ReturnTypes": []
  },
  {
    "ContainingType": "AuthorWebsiteAPI.Controllers.AuthController",
    "Method": "Login",
    "RelativePath": "api/Auth/login",
    "HttpMethod": "POST",
    "IsController": true,
    "Order": 0,
    "Parameters": [
      {
        "Name": "req",
        "Type": "AuthorWebsiteAPI.DTOs.LoginRequestDTO",
        "IsRequired": true
      }
    ],
    "ReturnTypes": []
  },
  {
    "ContainingType": "AuthorWebsiteAPI.Controllers.AuthController",
    "Method": "Logout",
    "RelativePath": "api/Auth/logout",
    "HttpMethod": "POST",
    "IsController": true,
    "Order": 0,
    "Parameters": [],
    "ReturnTypes": []
  },
  {
    "ContainingType": "AuthorWebsiteAPI.Controllers.AuthController",
    "Method": "Register",
    "RelativePath": "api/Auth/register",
    "HttpMethod": "POST",
    "IsController": true,
    "Order": 0,
    "Parameters": [
      {
        "Name": "req",
        "Type": "AuthorWebsiteAPI.DTOs.RegisterRequestDTO",
        "IsRequired": true
      }
    ],
    "ReturnTypes": []
  },
  {
    "ContainingType": "AuthorWebsiteAPI.Controllers.AuthController",
    "Method": "ResetPassword",
    "RelativePath": "api/Auth/reset-password",
    "HttpMethod": "POST",
    "IsController": true,
    "Order": 0,
    "Parameters": [
      {
        "Name": "dto",
        "Type": "AuthorWebsiteAPI.DTOs.ResetDto",
        "IsRequired": true
      }
    ],
    "ReturnTypes": []
  },
  {
    "ContainingType": "AuthorWebsiteAPI.Controllers.BooksController",
    "Method": "Get",
    "RelativePath": "api/Books",
    "HttpMethod": "GET",
    "IsController": true,
    "Order": 0,
    "Parameters": [],
    "ReturnTypes": []
  },
  {
    "ContainingType": "AuthorWebsiteAPI.Controllers.BooksController",
    "Method": "Add",
    "RelativePath": "api/Books",
    "HttpMethod": "POST",
    "IsController": true,
    "Order": 0,
    "Parameters": [
      {
        "Name": "book",
        "Type": "AuthorWebsiteAPI.Models.Book",
        "IsRequired": true
      }
    ],
    "ReturnTypes": []
  },
  {
    "ContainingType": "AuthorWebsiteAPI.Controllers.ContactController",
    "Method": "SendMessage",
    "RelativePath": "api/Contact",
    "HttpMethod": "POST",
    "IsController": true,
    "Order": 0,
    "Parameters": [
      {
        "Name": "data",
        "Type": "System.Object",
        "IsRequired": true
      }
    ],
    "ReturnTypes": []
  },
  {
    "ContainingType": "AuthorWebsiteAPI.Controllers.OrdersController",
    "Method": "GetAll",
    "RelativePath": "api/Orders",
    "HttpMethod": "GET",
    "IsController": true,
    "Order": 0,
    "Parameters": [],
    "ReturnTypes": []
  },
  {
    "ContainingType": "AuthorWebsiteAPI.Controllers.OrdersController",
    "Method": "CreateRazorpayOrder",
    "RelativePath": "api/Orders/create-razorpay-order",
    "HttpMethod": "POST",
    "IsController": true,
    "Order": 0,
    "Parameters": [
      {
        "Name": "dto",
        "Type": "AuthorWebsiteAPI.DTOs.RazorpayOrderDto",
        "IsRequired": true
      }
    ],
    "ReturnTypes": []
  },
  {
    "ContainingType": "AuthorWebsiteAPI.Controllers.OrdersController",
    "Method": "VerifyPayment",
    "RelativePath": "api/Orders/verify-payment",
    "HttpMethod": "POST",
    "IsController": true,
    "Order": 0,
    "Parameters": [
      {
        "Name": "dto",
        "Type": "AuthorWebsiteAPI.DTOs.RazorpayVerifyDto",
        "IsRequired": true
      }
    ],
    "ReturnTypes": []
  },
  {
    "ContainingType": "AuthorWebsiteAPI.Controllers.SpeechesController",
    "Method": "GetAll",
    "RelativePath": "api/Speeches",
    "HttpMethod": "GET",
    "IsController": true,
    "Order": 0,
    "Parameters": [],
    "ReturnTypes": []
  },
  {
    "ContainingType": "AuthorWebsiteAPI.Controllers.VideosController",
    "Method": "GetVideos",
    "RelativePath": "api/Videos",
    "HttpMethod": "GET",
    "IsController": true,
    "Order": 0,
    "Parameters": [],
    "ReturnTypes": []
  },
  {
    "ContainingType": "AuthorWebsiteAPI.Controllers.VideosController",
    "Method": "CheckAccess",
    "RelativePath": "api/Videos/access",
    "HttpMethod": "GET",
    "IsController": true,
    "Order": 0,
    "Parameters": [
      {
        "Name": "videoId",
        "Type": "System.Int32",
        "IsRequired": false
      }
    ],
    "ReturnTypes": []
  },
  {
    "ContainingType": "AuthorWebsiteAPI.Controllers.VideosController",
    "Method": "PurchaseVideo",
    "RelativePath": "api/Videos/purchase",
    "HttpMethod": "POST",
    "IsController": true,
    "Order": 0,
    "Parameters": [
      {
        "Name": "dto",
        "Type": "AuthorWebsiteAPI.Models.DTOs.PurchaseDto",
        "IsRequired": true
      }
    ],
    "ReturnTypes": []
  },
  {
    "ContainingType": "AuthorWebsiteAPI.Controllers.VideosController",
    "Method": "GetVideoStream",
    "RelativePath": "api/Videos/stream",
    "HttpMethod": "GET",
    "IsController": true,
    "Order": 0,
    "Parameters": [
      {
        "Name": "videoId",
        "Type": "System.Int32",
        "IsRequired": false
      }
    ],
    "ReturnTypes": []
  }
]